pypile/__init__.py
pypile/cli.py
pypile/pile_manager.py
pypile/report.py
pypile/setup.py
pypile/models/__init__.py
pypile/models/arrange_model.py
pypile/models/control_model.py
pypile/models/no_simu_model.py
pypile/models/pile_parser.py
pypile/models/pile_results_model.py
pypile/models/simu_pile_model.py
pypile/original/__init__.py
pypile/original/bcad_pile.py
pypile-1.0.2.dist-info/METADATA
pypile-1.0.2.dist-info/WHEEL
pypile-1.0.2.dist-info/entry_points.txt
pypile-1.0.2.dist-info/licenses/LICENSE
pypile-1.0.2.dist-info/RECORD
