Metadata-Version: 2.4
Name: pypile
Version: 1.0.2
Summary:  Bridge Foundation Spatial Static Analysis Program（桥梁基础结构空间静力分析程序）
License-File: LICENSE
Requires-Python: >=3.9
Requires-Dist: art>=6.4
Requires-Dist: loguru>=0.7.3
Requires-Dist: matplotlib>=3.7.5
Requires-Dist: numpy>1.24.4
Requires-Dist: pydantic>=2.10.6
Requires-Dist: tabulate>=0.9.0
